app/__init__.py
app/main.py
app/api/__init__.py
app/api/bluetooth.py
app/api/session.py
app/core/__init__.py
app/core/config.py
app/data/__init__.py
app/data/company_identifiers.py
app/data/mac_prefixes.py
app/models/__init__.py
app/models/bluetooth.py
app/models/session.py
app/services/__init__.py
app/services/ble_scanner.py
app/services/bluetooth_service.py
app/services/classic_scanner.py
app/services/windows_advanced_scanner.py
app/services/windows_scanner.py
app/utils/__init__.py
app/utils/bluetooth_utils.py
iflow_mcp_hypijump31_bluetooth_mcp_server-0.1.0.dist-info/licenses/LICENSE
mcp_sdk/__init__.py
mcp_sdk/bluetooth_tool.py
mcp_sdk/setup.py
iflow_mcp_hypijump31_bluetooth_mcp_server-0.1.0.dist-info/METADATA
iflow_mcp_hypijump31_bluetooth_mcp_server-0.1.0.dist-info/WHEEL
iflow_mcp_hypijump31_bluetooth_mcp_server-0.1.0.dist-info/entry_points.txt
iflow_mcp_hypijump31_bluetooth_mcp_server-0.1.0.dist-info/top_level.txt
iflow_mcp_hypijump31_bluetooth_mcp_server-0.1.0.dist-info/RECORD
