Metadata-Version: 2.4
Name: iflow-mcp_hypijump31_bluetooth-mcp-server
Version: 0.1.0
Summary: Bluetooth MCP Server for scanning and interacting with Bluetooth devices
Requires-Python: >=3.7
License-File: LICENSE
Requires-Dist: fastapi>=0.68.0
Requires-Dist: uvicorn>=0.15.0
Requires-Dist: pydantic>=1.8.2
Requires-Dist: bleak>=0.14.3
Requires-Dist: python-dotenv>=0.19.1
Requires-Dist: pydantic-settings>=2.0.0
Requires-Dist: mcp>=0.9.0
Requires-Dist: requests>=2.27.1
Dynamic: license-file
